{
  "timestamp": "2026.04.23 19:26:46",
  "oro": {
    "timestamp": "2026.04.23 20:26:39",
    "balance": 1084.08,
    "equity": 954.45,
    "flotante": -129.63,
    "ciclos": 80,
    "martingala": {
      "activa": false,
      "direccion": "",
      "nivel": 0,
      "precio": 0.0
    },
    "hedge": {
      "activo": true,
      "numero": 2,
      "objetivo": 51.53,
      "fondo": 40.27,
      "pct": 78.1
    }
  },
  "btc": {
    "timestamp": "2026.04.23 20:26:41",
    "balance": 1084.08,
    "equity": 954.41,
    "flotante": -129.67,
    "ciclos": 24,
    "martingala": {
      "activa": false,
      "direccion": "",
      "nivel": 0,
      "precio": 0.0
    },
    "hedge": {
      "activo": true,
      "numero": 1,
      "objetivo": 32.32,
      "fondo": 21.84,
      "pct": 67.6
    }
  },
  "ultimas_ops": []
}