{
  "timestamp": "2026.04.30 13:05:50",
  "ecosistema": {
    "bots_activos": 4,
    "balance_total": 4199.16,
    "equity_total": 3483.86,
    "flotante_total": -715.3,
    "ciclos_total": 51,
    "hedges_activos": 3,
    "ganancia_real_total": 24.68
  },
  "oro": {
    "timestamp": "2026.04.30 14:05:43",
    "balance": 1049.79,
    "equity": 871.01,
    "flotante": -178.78,
    "ciclos": 38,
    "ganancia_real": 20.11,
    "hucha_propia": 0.0,
    "hucha_aportado": 0.0,
    "martingala": {
      "activa": false,
      "direccion": "",
      "nivel": 0,
      "precio": 0.0
    },
    "hedge": {
      "activo": true,
      "numero": 1,
      "objetivo": 56.49,
      "fondo": 27.89,
      "pct": 49.4
    }
  },
  "btc": {
    "timestamp": "2026.04.30 14:05:45",
    "balance": 1049.79,
    "equity": 871.04,
    "flotante": -178.75,
    "ciclos": 4,
    "ganancia_real": 2.29,
    "hucha_propia": 0.0,
    "hucha_aportado": 1.91,
    "martingala": {
      "activa": true,
      "direccion": "SELL",
      "nivel": 1,
      "precio": 75719.98
    },
    "hedge": {
      "activo": false,
      "numero": 0,
      "objetivo": 0.0,
      "fondo": 0.0,
      "pct": 0.0
    }
  },
  "ger40": {
    "timestamp": "2026.04.30 14:05:43",
    "balance": 1049.79,
    "equity": 870.79,
    "flotante": -179.0,
    "ciclos": 3,
    "ganancia_real": 0.36,
    "hucha_propia": 0.0,
    "hucha_aportado": 0.0,
    "martingala": {
      "activa": true,
      "direccion": "SELL",
      "nivel": 2,
      "precio": 23857.44
    },
    "hedge": {
      "activo": true,
      "numero": 1,
      "objetivo": 4.89,
      "fondo": 3.22,
      "pct": 65.9
    }
  },
  "usdjpy": {
    "timestamp": "2026.04.30 14:05:45",
    "balance": 1049.79,
    "equity": 871.02,
    "flotante": -178.77,
    "ciclos": 6,
    "ganancia_real": 1.92,
    "hucha_propia": 0.0,
    "hucha_aportado": 0.0,
    "martingala": {
      "activa": false,
      "direccion": "",
      "nivel": 0,
      "precio": 0.0
    },
    "hedge": {
      "activo": true,
      "numero": 1,
      "objetivo": 32.53,
      "fondo": 0.0,
      "pct": 0.0
    }
  }
}