{
  "timestamp": "2026.05.05 10:34:58",
  "ecosistema": {
    "bots_activos": 4,
    "balance_total": 4114.52,
    "equity_total": 3655.49,
    "flotante_total": -459.03,
    "ciclos_total": 24,
    "hedges_activos": 1,
    "ganancia_real_total": 19.97
  },
  "oro": {
    "timestamp": "2026.05.05 11:34:35",
    "balance": 1028.63,
    "equity": 913.95,
    "flotante": -114.68,
    "ciclos": 15,
    "ganancia_real": 12.4,
    "hucha_propia": 0.0,
    "hucha_aportado": 0.0,
    "martingala": {
      "activa": false,
      "direccion": "",
      "nivel": 0,
      "precio": 0.0
    },
    "hedge": {
      "activo": true,
      "numero": 1,
      "objetivo": 51.1,
      "fondo": 8.23,
      "pct": 16.1
    }
  },
  "btc": {
    "timestamp": "2026.05.05 11:34:56",
    "balance": 1028.63,
    "equity": 914.13,
    "flotante": -114.5,
    "ciclos": 4,
    "ganancia_real": 2.16,
    "hucha_propia": 0.0,
    "hucha_aportado": 0.93,
    "martingala": {
      "activa": false,
      "direccion": "",
      "nivel": 0,
      "precio": 0.0
    },
    "hedge": {
      "activo": false,
      "numero": 0,
      "objetivo": 0.0,
      "fondo": 0.0,
      "pct": 0.0
    }
  },
  "ger40": {
    "timestamp": "2026.05.05 11:34:34",
    "balance": 1028.63,
    "equity": 913.95,
    "flotante": -114.68,
    "ciclos": 5,
    "ganancia_real": 5.41,
    "hucha_propia": 0.0,
    "hucha_aportado": 0.0,
    "martingala": {
      "activa": true,
      "direccion": "SELL",
      "nivel": 2,
      "precio": 23871.71
    },
    "hedge": {
      "activo": false,
      "numero": 0,
      "objetivo": 0.0,
      "fondo": 0.0,
      "pct": 0.0
    }
  },
  "usdjpy": {
    "timestamp": "2026.05.05 11:34:48",
    "balance": 1028.63,
    "equity": 913.46,
    "flotante": -115.17,
    "ciclos": 0,
    "ganancia_real": 0.0,
    "hucha_propia": 0.0,
    "hucha_aportado": 0.0,
    "martingala": {
      "activa": true,
      "direccion": "SELL",
      "nivel": 1,
      "precio": 156.65
    },
    "hedge": {
      "activo": false,
      "numero": 0,
      "objetivo": 0.0,
      "fondo": 0.0,
      "pct": 0.0
    }
  }
}