{
  "timestamp": "2026.05.06 15:40:41",
  "ecosistema": {
    "bots_activos": 4,
    "balance_total": 4195.8,
    "equity_total": 3745.74,
    "flotante_total": -450.06,
    "ciclos_total": 42,
    "hedges_activos": 2,
    "ganancia_real_total": 20.62
  },
  "oro": {
    "timestamp": "2026.05.06 16:40:14",
    "balance": 1048.95,
    "equity": 935.99,
    "flotante": -112.96,
    "ciclos": 23,
    "ganancia_real": 12.4,
    "hucha_propia": 0.0,
    "hucha_aportado": 0.0,
    "martingala": {
      "activa": true,
      "direccion": "BUY",
      "nivel": 1,
      "precio": 4695.54
    },
    "hedge": {
      "activo": true,
      "numero": 1,
      "objetivo": 52.15,
      "fondo": 25.28,
      "pct": 48.5
    }
  },
  "btc": {
    "timestamp": "2026.05.06 16:40:14",
    "balance": 1048.95,
    "equity": 935.99,
    "flotante": -112.96,
    "ciclos": 9,
    "ganancia_real": 2.4,
    "hucha_propia": 0.0,
    "hucha_aportado": 6.09,
    "martingala": {
      "activa": false,
      "direccion": "",
      "nivel": 0,
      "precio": 0.0
    },
    "hedge": {
      "activo": false,
      "numero": 0,
      "objetivo": 0.0,
      "fondo": 0.0,
      "pct": 0.0
    }
  },
  "ger40": {
    "timestamp": "2026.05.06 16:40:19",
    "balance": 1048.95,
    "equity": 937.26,
    "flotante": -111.69,
    "ciclos": 8,
    "ganancia_real": 5.52,
    "hucha_propia": 0.0,
    "hucha_aportado": 0.0,
    "martingala": {
      "activa": false,
      "direccion": "",
      "nivel": 0,
      "precio": 0.0
    },
    "hedge": {
      "activo": true,
      "numero": 1,
      "objetivo": 60.73,
      "fondo": 3.8,
      "pct": 6.3
    }
  },
  "usdjpy": {
    "timestamp": "2026.05.06 16:40:15",
    "balance": 1048.95,
    "equity": 936.5,
    "flotante": -112.45,
    "ciclos": 2,
    "ganancia_real": 0.3,
    "hucha_propia": 0.0,
    "hucha_aportado": 2.66,
    "martingala": {
      "activa": false,
      "direccion": "",
      "nivel": 0,
      "precio": 0.0
    },
    "hedge": {
      "activo": false,
      "numero": 0,
      "objetivo": 0.0,
      "fondo": 0.0,
      "pct": 0.0
    }
  }
}