{
  "timestamp": "2026.04.29 16:58:34",
  "ecosistema": {
    "bots_activos": 4,
    "balance_total": 4085.8,
    "equity_total": 4008.5,
    "flotante_total": -77.3,
    "ciclos_total": 24,
    "hedges_activos": 0,
    "ganancia_real_total": 21.51
  },
  "oro": {
    "timestamp": "2026.04.29 17:58:31",
    "balance": 1021.45,
    "equity": 1001.99,
    "flotante": -19.46,
    "ciclos": 20,
    "ganancia_real": 17.91,
    "hucha_propia": 5.97,
    "hucha_aportado": 0.0,
    "martingala": {
      "activa": true,
      "direccion": "SELL",
      "nivel": 2,
      "precio": 4519.08
    },
    "hedge": {
      "activo": false,
      "numero": 0,
      "objetivo": 0.0,
      "fondo": 0.0,
      "pct": 0.0
    }
  },
  "btc": {
    "timestamp": "2026.04.29 17:58:27",
    "balance": 1021.45,
    "equity": 1002.45,
    "flotante": -19.0,
    "ciclos": 2,
    "ganancia_real": 2.08,
    "hucha_propia": 0.69,
    "hucha_aportado": 0.0,
    "martingala": {
      "activa": true,
      "direccion": "BUY",
      "nivel": 1,
      "precio": 76814.27
    },
    "hedge": {
      "activo": false,
      "numero": 0,
      "objetivo": 0.0,
      "fondo": 0.0,
      "pct": 0.0
    }
  },
  "ger40": {
    "timestamp": "2026.04.29 17:58:29",
    "balance": 1021.45,
    "equity": 1002.36,
    "flotante": -19.09,
    "ciclos": 0,
    "ganancia_real": 0.0,
    "hucha_propia": 0.0,
    "hucha_aportado": 0.0,
    "martingala": {
      "activa": false,
      "direccion": "",
      "nivel": 0,
      "precio": 0.0
    },
    "hedge": {
      "activo": false,
      "numero": 0,
      "objetivo": 0.0,
      "fondo": 0.0,
      "pct": 0.0
    }
  },
  "usdjpy": {
    "timestamp": "2026.04.29 17:58:25",
    "balance": 1021.45,
    "equity": 1001.7,
    "flotante": -19.75,
    "ciclos": 2,
    "ganancia_real": 1.52,
    "hucha_propia": 0.51,
    "hucha_aportado": 0.0,
    "martingala": {
      "activa": true,
      "direccion": "BUY",
      "nivel": 1,
      "precio": 160.15
    },
    "hedge": {
      "activo": false,
      "numero": 0,
      "objetivo": 0.0,
      "fondo": 0.0,
      "pct": 0.0
    }
  }
}