{
  "timestamp": "2026.04.30 04:25:26",
  "ecosistema": {
    "bots_activos": 4,
    "balance_total": 4119.84,
    "equity_total": 3770.76,
    "flotante_total": -349.08,
    "ciclos_total": 35,
    "hedges_activos": 2,
    "ganancia_real_total": 22.67
  },
  "oro": {
    "timestamp": "2026.04.30 05:25:18",
    "balance": 1029.96,
    "equity": 941.97,
    "flotante": -87.99,
    "ciclos": 27,
    "ganancia_real": 18.66,
    "hucha_propia": 0.0,
    "hucha_aportado": 0.0,
    "martingala": {
      "activa": true,
      "direccion": "SELL",
      "nivel": 2,
      "precio": 4557.44
    },
    "hedge": {
      "activo": true,
      "numero": 1,
      "objetivo": 56.49,
      "fondo": 14.84,
      "pct": 26.3
    }
  },
  "btc": {
    "timestamp": "2026.04.30 05:25:25",
    "balance": 1029.96,
    "equity": 943.01,
    "flotante": -86.95,
    "ciclos": 3,
    "ganancia_real": 2.19,
    "hucha_propia": 0.0,
    "hucha_aportado": 0.97,
    "martingala": {
      "activa": false,
      "direccion": "",
      "nivel": 0,
      "precio": 0.0
    },
    "hedge": {
      "activo": false,
      "numero": 0,
      "objetivo": 0.0,
      "fondo": 0.0,
      "pct": 0.0
    }
  },
  "ger40": {
    "timestamp": "2026.04.30 05:25:20",
    "balance": 1029.96,
    "equity": 942.83,
    "flotante": -87.13,
    "ciclos": 0,
    "ganancia_real": 0.0,
    "hucha_propia": 0.0,
    "hucha_aportado": 0.0,
    "martingala": {
      "activa": false,
      "direccion": "",
      "nivel": 0,
      "precio": 0.0
    },
    "hedge": {
      "activo": true,
      "numero": 1,
      "objetivo": 5.55,
      "fondo": 0.0,
      "pct": 0.0
    }
  },
  "usdjpy": {
    "timestamp": "2026.04.30 05:25:23",
    "balance": 1029.96,
    "equity": 942.95,
    "flotante": -87.01,
    "ciclos": 5,
    "ganancia_real": 1.82,
    "hucha_propia": 0.0,
    "hucha_aportado": 2.77,
    "martingala": {
      "activa": true,
      "direccion": "BUY",
      "nivel": 1,
      "precio": 160.38
    },
    "hedge": {
      "activo": false,
      "numero": 0,
      "objetivo": 0.0,
      "fondo": 0.0,
      "pct": 0.0
    }
  }
}