{
  "timestamp": "2026.05.06 21:00:01",
  "ecosistema": {
    "bots_activos": 4,
    "balance_total": 4212.56,
    "equity_total": 3682.32,
    "flotante_total": -530.24,
    "ciclos_total": 46,
    "hedges_activos": 2,
    "ganancia_real_total": 20.62
  },
  "oro": {
    "timestamp": "2026.05.06 21:59:44",
    "balance": 1053.14,
    "equity": 920.58,
    "flotante": -132.56,
    "ciclos": 27,
    "ganancia_real": 12.4,
    "hucha_propia": 0.0,
    "hucha_aportado": 0.0,
    "martingala": {
      "activa": false,
      "direccion": "",
      "nivel": 0,
      "precio": 0.0
    },
    "hedge": {
      "activo": true,
      "numero": 1,
      "objetivo": 52.15,
      "fondo": 29.47,
      "pct": 56.5
    }
  },
  "btc": {
    "timestamp": "2026.05.06 21:59:48",
    "balance": 1053.14,
    "equity": 920.6,
    "flotante": -132.54,
    "ciclos": 9,
    "ganancia_real": 2.4,
    "hucha_propia": 0.0,
    "hucha_aportado": 6.09,
    "martingala": {
      "activa": true,
      "direccion": "BUY",
      "nivel": 1,
      "precio": 81825.91
    },
    "hedge": {
      "activo": false,
      "numero": 0,
      "objetivo": 0.0,
      "fondo": 0.0,
      "pct": 0.0
    }
  },
  "ger40": {
    "timestamp": "2026.05.06 22:00:01",
    "balance": 1053.14,
    "equity": 920.56,
    "flotante": -132.58,
    "ciclos": 8,
    "ganancia_real": 5.52,
    "hucha_propia": 0.0,
    "hucha_aportado": 0.0,
    "martingala": {
      "activa": true,
      "direccion": "BUY",
      "nivel": 1,
      "precio": 24929.68
    },
    "hedge": {
      "activo": true,
      "numero": 1,
      "objetivo": 60.69,
      "fondo": 3.8,
      "pct": 6.3
    }
  },
  "usdjpy": {
    "timestamp": "2026.05.06 21:59:45",
    "balance": 1053.14,
    "equity": 920.58,
    "flotante": -132.56,
    "ciclos": 2,
    "ganancia_real": 0.3,
    "hucha_propia": 0.0,
    "hucha_aportado": 2.66,
    "martingala": {
      "activa": true,
      "direccion": "SELL",
      "nivel": 1,
      "precio": 156.09
    },
    "hedge": {
      "activo": false,
      "numero": 0,
      "objetivo": 0.0,
      "fondo": 0.0,
      "pct": 0.0
    }
  }
}