{
  "timestamp": "2026.04.29 10:24:33",
  "ecosistema": {
    "bots_activos": 4,
    "balance_total": 4056.24,
    "equity_total": 4008.17,
    "flotante_total": -48.07,
    "ciclos_total": 12,
    "hedges_activos": 0,
    "ganancia_real_total": 11.27
  },
  "oro": {
    "timestamp": "2026.04.29 11:24:24",
    "balance": 1014.06,
    "equity": 1002.03,
    "flotante": -12.03,
    "ciclos": 11,
    "ganancia_real": 10.38,
    "hucha_propia": 3.46,
    "hucha_aportado": 0.0,
    "martingala": {
      "activa": true,
      "direccion": "SELL",
      "nivel": 1,
      "precio": 4566.35
    },
    "hedge": {
      "activo": false,
      "numero": 0,
      "objetivo": 0.0,
      "fondo": 0.0,
      "pct": 0.0
    }
  },
  "btc": {
    "timestamp": "2026.04.29 11:24:26",
    "balance": 1014.06,
    "equity": 1002.03,
    "flotante": -12.03,
    "ciclos": 1,
    "ganancia_real": 0.89,
    "hucha_propia": 0.3,
    "hucha_aportado": 0.0,
    "martingala": {
      "activa": true,
      "direccion": "SELL",
      "nivel": 1,
      "precio": 76268.72
    },
    "hedge": {
      "activo": false,
      "numero": 0,
      "objetivo": 0.0,
      "fondo": 0.0,
      "pct": 0.0
    }
  },
  "eurusd": {
    "timestamp": "2026.04.29 11:24:24",
    "balance": 1014.06,
    "equity": 1002.02,
    "flotante": -12.04,
    "ciclos": 0,
    "ganancia_real": 0.0,
    "hucha_propia": 0.0,
    "hucha_aportado": 0.0,
    "martingala": {
      "activa": true,
      "direccion": "BUY",
      "nivel": 1,
      "precio": 1.17
    },
    "hedge": {
      "activo": false,
      "numero": 0,
      "objetivo": 0.0,
      "fondo": 0.0,
      "pct": 0.0
    }
  },
  "usdjpy": {
    "timestamp": "2026.04.29 11:24:27",
    "balance": 1014.06,
    "equity": 1002.09,
    "flotante": -11.97,
    "ciclos": 0,
    "ganancia_real": 0.0,
    "hucha_propia": 0.0,
    "hucha_aportado": 0.0,
    "martingala": {
      "activa": true,
      "direccion": "BUY",
      "nivel": 1,
      "precio": 159.6
    },
    "hedge": {
      "activo": false,
      "numero": 0,
      "objetivo": 0.0,
      "fondo": 0.0,
      "pct": 0.0
    }
  }
}