{
  "timestamp": "2026.04.28 16:50:13",
  "oro": {
    "timestamp": "2026.04.28 17:50:13",
    "balance": 1062.74,
    "equity": 972.49,
    "flotante": -90.25,
    "ciclos": 34,
    "martingala": {
      "activa": false,
      "direccion": "",
      "nivel": 0,
      "precio": 0.0
    },
    "hedge": {
      "activo": true,
      "numero": 1,
      "objetivo": 54.09,
      "fondo": 43.79,
      "pct": 81.0
    }
  },
  "btc": {
    "timestamp": "2026.04.28 17:50:09",
    "balance": 1062.74,
    "equity": 972.49,
    "flotante": -90.25,
    "ciclos": 13,
    "martingala": {
      "activa": false,
      "direccion": "",
      "nivel": 0,
      "precio": 0.0
    },
    "hedge": {
      "activo": true,
      "numero": 1,
      "objetivo": 36.16,
      "fondo": 12.79,
      "pct": 35.4
    }
  },
  "ultimas_ops": []
}